MANIFEST.in
README.md
setup.py
src/django_vernissage.egg-info/PKG-INFO
src/django_vernissage.egg-info/SOURCES.txt
src/django_vernissage.egg-info/dependency_links.txt
src/django_vernissage.egg-info/not-zip-safe
src/django_vernissage.egg-info/requires.txt
src/django_vernissage.egg-info/top_level.txt
src/vernissage/__init__.py
src/vernissage/admin.py
src/vernissage/cms_plugins.py
src/vernissage/models.py
src/vernissage/settings.py
src/vernissage/migrations/0001_initial.py
src/vernissage/migrations/0002_auto__add_galleryplugin.py
src/vernissage/migrations/0003_auto__del_field_galleryplugin_gallery__add_field_galleryplugin_gallery.py
src/vernissage/migrations/0004_auto__chg_field_image_description__chg_field_image_alt.py
src/vernissage/migrations/__init__.py
src/vernissage/templates/vernissage/carousel.html
src/vernissage/templates/vernissage/gallery_plugin.html