Metadata-Version: 1.1
Name: django-vernissage
Version: 0.0.13
Summary: An extremely simple dynamic TemplateView for django
Home-page: https://github.com/Lacrymology/django-vernissage
Author: Tomas Neme
Author-email: lacrymology@gmail.com
License: MIT
Keywords: django,image-gallery,filer django-cms
Platform: UNKNOWN
Classifier: Development Status :: 3 - Alpha
Classifier: Topic :: Utilities
Classifier: License :: OSI Approved :: MIT License
